Mapserver72ZhongwenWendang/README.md
Mapserver72ZhongwenWendang/__init__.py
Mapserver72ZhongwenWendang/__main__.py
Mapserver72ZhongwenWendang/file.epub
Mapserver72ZhongwenWendang/index.html
Mapserver72ZhongwenWendang/css/__init__.py
Mapserver72ZhongwenWendang/css/annotations.css
Mapserver72ZhongwenWendang/css/main.css
Mapserver72ZhongwenWendang/css/normalize.css
Mapserver72ZhongwenWendang/css/popup.css
Mapserver72ZhongwenWendang/font/__init__.py
Mapserver72ZhongwenWendang/font/fontello.eot
Mapserver72ZhongwenWendang/font/fontello.svg
Mapserver72ZhongwenWendang/font/fontello.ttf
Mapserver72ZhongwenWendang/font/fontello.woff
Mapserver72ZhongwenWendang/img/__init__.py
Mapserver72ZhongwenWendang/img/annotator-glyph-sprite.png
Mapserver72ZhongwenWendang/img/annotator-icon-sprite.png
Mapserver72ZhongwenWendang/img/apple-touch-icon.png
Mapserver72ZhongwenWendang/img/cancelfullscreen.png
Mapserver72ZhongwenWendang/img/close.png
Mapserver72ZhongwenWendang/img/fullscreen.png
Mapserver72ZhongwenWendang/img/loader.gif
Mapserver72ZhongwenWendang/img/menu-icon.png
Mapserver72ZhongwenWendang/img/save.png
Mapserver72ZhongwenWendang/img/saved.png
Mapserver72ZhongwenWendang/img/settings-s.png
Mapserver72ZhongwenWendang/img/settings.png
Mapserver72ZhongwenWendang/img/star.png
Mapserver72ZhongwenWendang/js/__init__.py
Mapserver72ZhongwenWendang/js/epub.js
Mapserver72ZhongwenWendang/js/epub.min.js
Mapserver72ZhongwenWendang/js/epub.min.map
Mapserver72ZhongwenWendang/js/hooks.min.js
Mapserver72ZhongwenWendang/js/hooks.min.map
Mapserver72ZhongwenWendang/js/reader.js
Mapserver72ZhongwenWendang/js/reader.js.map
Mapserver72ZhongwenWendang/js/reader.min.js
Mapserver72ZhongwenWendang/js/reader.min.map
Mapserver72ZhongwenWendang/js/hooks/__init__.py
Mapserver72ZhongwenWendang/js/hooks/extensions/__init__.py
Mapserver72ZhongwenWendang/js/hooks/extensions/highlight.js
Mapserver72ZhongwenWendang/js/libs/__init__.py
Mapserver72ZhongwenWendang/js/libs/jquery.min.js
mapserver_7_2_zhongwen_wendang-2024.3.5.0.dist-info/METADATA
mapserver_7_2_zhongwen_wendang-2024.3.5.0.dist-info/WHEEL
mapserver_7_2_zhongwen_wendang-2024.3.5.0.dist-info/entry_points.txt
mapserver_7_2_zhongwen_wendang-2024.3.5.0.dist-info/top_level.txt
mapserver_7_2_zhongwen_wendang-2024.3.5.0.dist-info/RECORD
